{
  "project_info": {
    "project_number": "135910574790",
    "project_id": "hrdn-61418",
    "storage_bucket": "hrdn-61418.appspot.com"
  },
  "client": [
    {
      "client_info": {
        "mobilesdk_app_id": "1:135910574790:android:f613c30928ee1e5be9e5c7",
        "android_client_info": {
          "package_name": "com.example.rhdn_app"
        }
      },
      "oauth_client": [
        {
          "client_id": "135910574790-fp2fp49n8t95j8059b9lapqapqdjd1v0.apps.googleusercontent.com",
          "client_type": 3
        }
      ],
      "api_key": [
        {
          "current_key": "AIzaSyB3K1n2dMAQwKRK6TLanM_uuKYJEIk-AEE"
        }
      ],
      "services": {
        "appinvite_service": {
          "other_platform_oauth_client": [
            {
              "client_id": "135910574790-fp2fp49n8t95j8059b9lapqapqdjd1v0.apps.googleusercontent.com",
              "client_type": 3
            }
          ]
        }
      }
    }
  ],
  "configuration_version": "1"
}